wmain/__init__.py
wmain/api/__init__.py
wmain/api/pan123.py
wmain/api/pan123.pyi
wmain_api-0.1.3.dist-info/METADATA
wmain_api-0.1.3.dist-info/WHEEL
wmain_api-0.1.3.dist-info/RECORD
