Metadata-Version: 2.4
Name: wmain-api
Version: 0.1.3
Summary: wmain 负责封装网络请求的包, 支持 123pan, 阿里云, 云码, 超级鹰等
License: MIT
Author: wmain-api@wyn.wiki
Requires-Python: >=3.10,<4.0
Classifier: License :: OSI Approved :: MIT License
Classifier: Programming Language :: Python :: 3
Classifier: Programming Language :: Python :: 3.10
Classifier: Programming Language :: Python :: 3.11
Classifier: Programming Language :: Python :: 3.12
Classifier: Programming Language :: Python :: 3.13
Classifier: Programming Language :: Python :: 3.14
Requires-Dist: wmain-base (==0.1.1)
